pyammo/__init__.py
pyammo/characters/__init__.py
pyammo/characters/characters.py
pyammo/characters/elemental_powers.py
pyammo/characters/positions.py
pyammo/characters/possesions.py
pyammo/characters/skills.py
pyammo/characters/skins.py
pyammo/client.py
pyammo-0.0.1.dist-info/LICENSE
pyammo-0.0.1.dist-info/METADATA
pyammo-0.0.1.dist-info/WHEEL
pyammo-0.0.1.dist-info/RECORD
