Metadata-Version: 2.1
Name: pyammo
Version: 0.0.1
Summary: A python library for the Artifacts MMO.
Author: Joaquín Barotto
Author-email: joaquinbarotto@gmail.com
Requires-Python: >=3.11,<4.0
Classifier: Programming Language :: Python :: 3
Classifier: Programming Language :: Python :: 3.11
Requires-Dist: requests (>=2.32.3,<3.0.0)
